{"createdAt":"2024-05-17T13:22:43.956Z","updatedAt":"2024-05-17T13:59:35.000Z","id":"mRdYcgdLG7vmfsTM","name":"n8n receiver","active":true,"nodes":[{"parameters":{"fieldToSplitOut":"body.urls","options":{}},"id":"f15b15bc-5f82-44e4-b76b-fd9026bfae84","name":"Split Out","type":"n8n-nodes-base.splitOut","typeVersion":1,"position":[1040,400]},{"parameters":{"mode":"runOnceForEachItem","jsCode":"let cleanedUrl = $input.item.json[\"body.urls\"];\ndelete $input.item.json[\"body.urls\"];\n\nif (!cleanedUrl.startsWith(\"http\")) {\n  cleanedUrl = \"https://\" + cleanedUrl;\n}\n\nif (!cleanedUrl.endsWith(\"/\")) {\n  cleanedUrl = cleanedUrl + \"/\";\n}\n\n$input.item.json.url = cleanedUrl;\nreturn $input.item;"},"id":"77f74a3d-e1de-4076-b961-86ae9910f20f","name":"Code","type":"n8n-nodes-base.code","typeVersion":2,"position":[1260,400]},{"parameters":{"batchSize":5,"options":{}},"id":"8a1b04e9-a95a-495e-afd9-7bbdccfcf9c9","name":"Loop Over Items","type":"n8n-nodes-base.splitInBatches","typeVersion":3,"position":[1620,380]},{"parameters":{"workflowId":"4Cm6d0j4HovNxxu5","mode":"each","options":{"waitForSubWorkflow":true}},"id":"7b460f19-c99d-4f0d-a8c8-376abaa13e45","name":"Execute Workflow","type":"n8n-nodes-base.executeWorkflow","typeVersion":1,"position":[2060,400]},{"parameters":{"assignments":{"assignments":[{"id":"ddeb2f43-ad2d-4b13-8fcb-0b6ba6669708","name":"site","value":"={{ $json.url }}","type":"string"}]},"options":{}},"id":"21cc77f2-69e3-46b6-9189-cfa2ccf803fa","name":"Edit Fields","type":"n8n-nodes-base.set","typeVersion":3.3,"position":[1860,400]},{"parameters":{"method":"POST","url":"={{ $('Webhook').item.json.body.callbackUrl }}","sendBody":true,"bodyParameters":{"parameters":[{"name":"url","value":"={{ $('Edit Fields').item.json.site }}"},{"name":"data","value":"={{ $json }}"}]},"options":{}},"id":"835a1389-8ff7-47dc-a94d-a9a5d2a747d4","name":"HTTP Request","type":"n8n-nodes-base.httpRequest","typeVersion":4.2,"position":[2760,480]},{"parameters":{"workflowId":"BuLwXmCknryE1mMw","mode":"each","options":{"waitForSubWorkflow":true}},"id":"3c22f579-ee30-4b2d-9bde-f4a878dc36af","name":"pagespeedInsights","type":"n8n-nodes-base.executeWorkflow","typeVersion":1,"position":[2060,580]},{"parameters":{"mode":"combine","combinationMode":"mergeByPosition","options":{"clashHandling":{"values":{"resolveClash":"addSuffix"}}}},"id":"120ab0b4-8ad3-4aec-97b3-77975b85a645","name":"Merge","type":"n8n-nodes-base.merge","typeVersion":2.1,"position":[2280,480]},{"parameters":{"assignments":{"assignments":[{"id":"daa60b97-1eab-47ce-a56d-41438cb3d6d6","name":"data.Services","value":"={{ $json.Services_1 }}","type":"array"},{"id":"28e5381a-22d0-42b2-9cc6-e5ec668a41cb","name":"data.CompanyInfo","value":"={{ $json.CompanyInfo_1 }}","type":"object"},{"id":"fe36eef6-f0d2-487b-8ec7-0dcce2fac4b5","name":"data.Reviews","value":"={{ $json.Reviews_1 }}","type":"array"},{"id":"fc4255cc-eab0-42ea-aee5-f892f1a5a23d","name":"data.SocialMediaLinks","value":"={{ $json.SocialMediaLinks_1 }}","type":"array"},{"id":"7e08d25a-7eff-4f40-84b0-1ca757c4a059","name":"scores.performance","value":"={{ $json.performance_2 }}","type":"number"},{"id":"d01e139f-268f-4d6d-823a-72b87614da80","name":"scores.accessibility","value":"={{ $json.accessibility_2 }}","type":"number"},{"id":"66cd8b40-a9bd-4319-b2e7-0d6ae9b3a4e7","name":"scores.bestPractices","value":"={{ $json.bestPractices_2 }}","type":"number"},{"id":"ec95e9ab-feec-4d43-ae90-8683ef6df9c8","name":"scores.seo","value":"={{ $json.seo_2 }}","type":"number"}]},"options":{}},"id":"d8493f47-e964-4dfa-a590-0817f772ba23","name":"Edit Fields1","type":"n8n-nodes-base.set","typeVersion":3.3,"position":[2500,480]},{"parameters":{"httpMethod":"POST","path":"41b5b4ca-9faa-4c51-8db6-8bb0969bad67","options":{}},"id":"69b6ba28-8e63-4aba-9e0e-c45f4673d4f4","name":"Webhook","type":"n8n-nodes-base.webhook","typeVersion":2,"position":[820,400],"webhookId":"41b5b4ca-9faa-4c51-8db6-8bb0969bad67"}],"connections":{"Split Out":{"main":[[{"node":"Code","type":"main","index":0}]]},"Code":{"main":[[{"node":"Loop Over Items","type":"main","index":0}]]},"Loop Over Items":{"main":[[],[{"node":"Edit Fields","type":"main","index":0}]]},"Edit Fields":{"main":[[{"node":"Execute Workflow","type":"main","index":0},{"node":"pagespeedInsights","type":"main","index":0}]]},"Execute Workflow":{"main":[[{"node":"Merge","type":"main","index":0}]]},"HTTP Request":{"main":[[{"node":"Loop Over Items","type":"main","index":0}]]},"pagespeedInsights":{"main":[[{"node":"Merge","type":"main","index":1}]]},"Merge":{"main":[[{"node":"Edit Fields1","type":"main","index":0}]]},"Edit Fields1":{"main":[[{"node":"HTTP Request","type":"main","index":0}]]},"Webhook":{"main":[[{"node":"Split Out","type":"main","index":0}]]}},"settings":{"executionOrder":"v1"},"staticData":null,"meta":{"templateCredsSetupCompleted":true},"pinData":{},"versionId":"eb2e340d-65a2-4522-8966-615a937f6603","triggerCount":1,"tags":[{"createdAt":"2024-05-02T14:44:58.922Z","updatedAt":"2024-05-02T14:44:58.922Z","id":"93Tla7jmYw7BwnIS","name":"Project Insite"}]}